main.py
cli/__init__.py
cli/init_profile.py
config/__init__.py
config/accessors.py
config/config_loader.py
config/profile_schema.py
core/__init__.py
core/correlator.py
core/explain.py
core/paths.py
core/snapshot_diff.py
output/__init__.py
output/html_report.py
output/markdown_report.py
output/templates/base.html
output/templates/report_index.html
output/templates/report_template.html
output/templates/partials/footer.html
output/templates/partials/header.html
output/templates/partials/plugin_section.html
output/templates/static/app.js
output/templates/static/brand.css
output/templates/static/logo.png
plugins/__init__.py
plugins/ci_cd.py
plugins/cost.py
plugins/docker.py
plugins/gitops.py
plugins/helm.py
plugins/kubernetes.py
plugins/secrets.py
plugins/terraform.py
utils/__init__.py
utils/audit_log.py
utils/demo_fixtures.py
utils/logger.py
utils/publisher.py
utils/reporter.py
utils/sanitize.py
utils/secret_loader.py
utils/state_loader.py
web/__init__.py
web/auth.py
web/server.py
snapcheck_cli-1.1.0.dist-info/METADATA
snapcheck_cli-1.1.0.dist-info/WHEEL
snapcheck_cli-1.1.0.dist-info/entry_points.txt
snapcheck_cli-1.1.0.dist-info/top_level.txt
snapcheck_cli-1.1.0.dist-info/RECORD
