Metadata-Version: 2.4
Name: snapcheck-cli
Version: 1.1.0
Summary: SnapCheck — Unified DevOps/MLOps Audit & Correlation Engine
Author: SnapCheck Team
Keywords: devops,security,kubernetes,terraform,cicd,cost
Classifier: Programming Language :: Python :: 3
Classifier: License :: OSI Approved :: MIT License
Classifier: Operating System :: OS Independent
Requires-Python: >=3.9
Requires-Dist: click<9,>=8.1
Requires-Dist: PyYAML<7,>=6
Requires-Dist: rich<14,>=13
Requires-Dist: Jinja2<4,>=3.1
Requires-Dist: tabulate<0.10,>=0.9
Requires-Dist: boto3<2,>=1.34
Requires-Dist: kubernetes<31,>=29
Requires-Dist: GitPython<4,>=3.1
Requires-Dist: requests<3,>=2.31
Requires-Dist: pydantic<3,>=2.8
Requires-Dist: python-dateutil<3,>=2.8
Requires-Dist: fastapi<1,>=0.111
Requires-Dist: uvicorn[standard]<1,>=0.29
Requires-Dist: authlib<2,>=1.3
Requires-Dist: python-jose[cryptography]<4,>=3.3
Requires-Dist: pyjwt<3,>=2.8
Requires-Dist: openai<2,>=1
Requires-Dist: itsdangerous>=2.1
